satori_gensokyo/__init__.py
satori_gensokyo/characters.toml
satori_gensokyo/satori.py
satori_gensokyo-0.2.1.dist-info/entry_points.txt
satori_gensokyo-0.2.1.dist-info/LICENSE
satori_gensokyo-0.2.1.dist-info/WHEEL
satori_gensokyo-0.2.1.dist-info/METADATA
satori_gensokyo-0.2.1.dist-info/RECORD
